ragnosis/__init__.py
ragnosis/evaluation.py
diragnosis-0.0.0.dist-info/METADATA
diragnosis-0.0.0.dist-info/WHEEL
diragnosis-0.0.0.dist-info/top_level.txt
diragnosis-0.0.0.dist-info/RECORD
