Metadata-Version: 2.2
Name: diragnosis
Version: 0.0.0
Summary: RAGnosis - Diagnose the performance of your RAG!
Author-email: Clelia Astra Bertelli <astraberte9@gmail.com>
Project-URL: Homepage, https://github.com/AstraBert/RAGnosis
Project-URL: Issues, https://github.com/AstraBert/RAGnosis/issues
Classifier: Programming Language :: Python :: 3
Classifier: License :: OSI Approved :: MIT License
Classifier: Operating System :: OS Independent
Requires-Python: >=3.10
Requires-Dist: llama-index
Requires-Dist: llama-index-embeddings-openai
Requires-Dist: llama-index-embeddings-huggingface
Requires-Dist: llama-index-embeddings-cohere
Requires-Dist: llama-index-embeddings-mistralai
Requires-Dist: llama-index-llms-openai
Requires-Dist: llama-index-llms-cohere
Requires-Dist: llama-index-llms-groq
Requires-Dist: llama-index-llms-mistralai
Requires-Dist: llama-index-llms-anthropic
Requires-Dist: llama-index-vector-stores-qdrant
Requires-Dist: fastembed
Requires-Dist: qdrant_client
Requires-Dist: pydantic
Requires-Dist: pandas
